.VERSION
AUTHORS.rst
CONTRIBUTING.rst
HISTORY.rst
LICENSE
MANIFEST.in
Pipfile
Pipfile.lock
README.rst
USAGE.rst
dev-requirements.txt
requirements.txt
setup.cfg
setup.py
controltowerlib/.VERSION
controltowerlib/AUTHORS.rst
controltowerlib/CONTRIBUTING.rst
controltowerlib/HISTORY.rst
controltowerlib/LICENSE
controltowerlib/Pipfile
controltowerlib/Pipfile.lock
controltowerlib/README.rst
controltowerlib/USAGE.rst
controltowerlib/__init__.py
controltowerlib/_version.py
controltowerlib/controltowerlib.py
controltowerlib/controltowerlibexceptions.py
controltowerlib/dev-requirements.txt
controltowerlib/requirements.txt
controltowerlib.egg-info/PKG-INFO
controltowerlib.egg-info/SOURCES.txt
controltowerlib.egg-info/dependency_links.txt
controltowerlib.egg-info/not-zip-safe
controltowerlib.egg-info/requires.txt
controltowerlib.egg-info/top_level.txt
controltowerlib/__pycache__/__init__.cpython-37.pyc
controltowerlib/__pycache__/_version.cpython-37.pyc
controltowerlib/__pycache__/controltowerlib.cpython-37.pyc
controltowerlib/__pycache__/controltowerlibexceptions.cpython-37.pyc
controltowerlib/resources/__init__.py
controltowerlib/resources/configuration.py
controltowerlib/resources/resources.py
controltowerlib/resources/__pycache__/__init__.cpython-37.pyc
controltowerlib/resources/__pycache__/configuration.cpython-37.pyc
controltowerlib/resources/__pycache__/resources.cpython-37.pyc
docs/Makefile
docs/authors.rst
docs/conf.py
docs/contributing.rst
docs/controltowerlib.rst
docs/history.rst
docs/index.rst
docs/installation.rst
docs/modules.rst
docs/readme.rst
docs/usage.rst