Metadata-Version: 1.1
Name: controltowerlib
Version: 0.4.0
Summary: A library to provide access to AWS service catalog provided by Control Tower and basic functionality with interfacing with it.
Home-page: https://github.com/schubergphilis/controltowerlib.git
Author: Costas Tyfoxylos
Author-email: ctyfoxylos@schubergphilis.com
License: MIT
Keywords: controltowerlib
Platform: UNKNOWN
Classifier: Development Status :: 4 - Beta
Classifier: Intended Audience :: Developers
Classifier: License :: OSI Approved :: MIT License
Classifier: Natural Language :: English
Classifier: Programming Language :: Python :: 3.7
